slanggen/__init__.py
slanggen/custom_logger.py
slanggen/datatools.py
slanggen/main.py
slanggen/models.py
slanggen-0.3.1.dist-info/METADATA
slanggen-0.3.1.dist-info/WHEEL
slanggen-0.3.1.dist-info/RECORD
