Metadata-Version: 2.3
Name: slanggen
Version: 0.3.1
Summary: generate slang
Author-email: Raoul Grouls <Raoul.Grouls@han.nl>
Requires-Python: >=3.10
Requires-Dist: loguru>=0.7.2
Requires-Dist: matplotlib>=3.9.2
Requires-Dist: numpy
Requires-Dist: tokenizers>=0.19.1
Requires-Dist: torch>=2.0
Provides-Extra: scrape
Requires-Dist: beautifulsoup4>=4.12.3; extra == 'scrape'
